{"anatomy.md":"Ci7eKTXZ","assembly.md":"2r1BL38d","bridge.md":"YzQJhNEp","concurrency.md":"B2kYbe3a","config.md":"DoOHmho-","debugging.md":"C9wOUjqv","index.md":"BXqjb92r","interfaces.md":"C4z6hV5s","intro.md":"DeLDwLm0","junior-path.md":"DgYCnwyk","lessons_01-server.md":"Bky-kMB9","lessons_02-structure.md":"Dkrr7-oo","lessons_03-data.md":"DaXl9Fyi","lessons_04-interaction.md":"DO122MUU","lessons_05-maps.md":"Bsqry84X","lessons_07-templating.md":"C3ZNEY5x","lessons_10-errors.md":"B2EizrFE","lessons_11-json.md":"C7SsUzmL","logic.md":"BE2DPlo3","loops.md":"DqdQrZQZ","memory-store.md":"Dj-rfcUV","middleware.md":"76bg4o9E","models.md":"qOlxjXvd","postgres.md":"2uQGkwUL","setup.md":"Clq2bq4k","signals.md":"DJPHVkRT","testing.md":"ZDh6B49t","validation.md":"-m5ZkhT3","variables.md":"DPIhPb9x","workflow.md":"BvZv20d1"}
